numerai_era_data/__init__.py
numerai_era_data/date_utils.py
numerai_era_data/era_data_api.py
numerai_era_data/data_sources/__init__.py
numerai_era_data/data_sources/base_data_source.py
numerai_era_data/data_sources/ds_bls.py
numerai_era_data/data_sources/ds_calendar.py
numerai_era_data/data_sources/ds_markets.py
numerai_era_data/data_sources/ds_wei.py
numerai_era_data-1.0.0.dist-info/LICENSE
numerai_era_data-1.0.0.dist-info/METADATA
numerai_era_data-1.0.0.dist-info/WHEEL
numerai_era_data-1.0.0.dist-info/top_level.txt
numerai_era_data-1.0.0.dist-info/RECORD
