Metadata-Version: 2.1
Name: numerai_era_data
Version: 1.0.0
Summary: era-level data for Numerai
Author-email: Gregory Morse <gregorymorse07@gmail.com>
License-File: LICENSE
Requires-Dist: pandas
Requires-Dist: pyarrow
Requires-Dist: yfinance
Provides-Extra: dev
Requires-Dist: black ; extra == 'dev'
Requires-Dist: isort ; extra == 'dev'
Requires-Dist: mock ; extra == 'dev'
Requires-Dist: pytest ; extra == 'dev'
Requires-Dist: ruff ; extra == 'dev'
